cycles/__init__.py
cycles/cube.py
cycles/cycles.cpython-313-darwin.so
cycles/cycles.pyi
cycles/cycles.pyx
cycles/group.py
cycles/named_group.py
cycles/operator.py
cycles/predicates.py
cycles/schreier_sims.cpython-313-darwin.so
cycles/schreier_sims.pyx
cycles/special_orthogonal_group.py
cycles/special_unitary_group.py
cycles/version.py
cycles/clifford/__init__.py
cycles/clifford/chp.py
cycles/clifford/chp_numpy.py
cycles/clifford/group.py
cycles/clifford/paulis.py
pycycles-1.0.10.dist-info/licenses/LICENSE
pycycles-1.0.10.dist-info/METADATA
pycycles-1.0.10.dist-info/WHEEL
pycycles-1.0.10.dist-info/top_level.txt
pycycles-1.0.10.dist-info/RECORD
